[
  {
    "patterns": [
      {
        "id": "KR-PN-0000050864",
        "name": "배수",
        "units": [
          {
            "id": "KR-UN-0000006334",
            "name": "배수",
            "datas": [
              "KR-DA-0000000062",
              "KR-DA-0000050600",
              "KR-DA-0000003687",
              "KR-DA-0000003688",
              "KR-DA-0000000060",
              "KR-DA-0000050601",
              "KR-DA-0000019539",
              "KR-DA-0000050602",
              "KR-DA-0000000061"
            ]
          },
          {
            "id": "KR-UN-0000004803",
            "name": "배수",
            "datas": [
              "KR-DA-0000050635",
              "KR-DA-0000000068",
              "KR-DA-0000000067",
              "KR-DA-0000050633",
              "KR-DA-0000000066",
              "KR-DA-0000050632",
              "KR-DA-0000050634",
              "KR-DA-0000050631"
            ]
          }
        ]
      }
    ]
  },
  {
    "patterns": [
      {
        "id": "KR-PN-0000050871",
        "name": "약수와 배수의 성질",
        "units": [
          {
            "id": "KR-UN-0000004804",
            "name": "약수와 배수의 성질",
            "datas": [
              "KR-DA-0000011527",
              "KR-DA-0000050639",
              "KR-DA-0000003630",
              "KR-DA-0000050637",
              "KR-DA-0000003690",
              "KR-DA-0000003631",
              "KR-DA-0000003691",
              "KR-DA-0000050640",
              "KR-DA-0000050638",
              "KR-DA-0000050636"
            ]
          }
        ]
      }
    ]
  },
  {
    "patterns": [
      {
        "id": "KR-PN-0000050874",
        "name": "소수",
        "units": [
          {
            "id": "KR-UN-0000021711",
            "name": "조건을 만족하는 자연수의 개수 구하기",
            "datas": [
              "KR-DA-0000051447",
              "KR-DA-0000051452",
              "KR-DA-0000051446",
              "KR-DA-0000051450",
              "KR-DA-0000051449",
              "KR-DA-0000051448",
              "KR-DA-0000051451",
              "KR-DA-0000051445"
            ]
          },
          {
            "id": "KR-UN-0000021713",
            "name": "조건을 만족하는 자연수 구하기",
            "datas": [
              "KR-DA-0000051461",
              "KR-DA-0000051454",
              "KR-DA-0000051455",
              "KR-DA-0000051460",
              "KR-DA-0000051458",
              "KR-DA-0000051457",
              "KR-DA-0000063392",
              "KR-DA-0000051453"
            ]
          }
        ]
      }
    ]
  },
  {
    "patterns": [
      {
        "id": "KR-PN-0000050881",
        "name": "합성수",
        "units": [
          {
            "id": "KR-UN-0000004807",
            "name": "합성수 개수 구하기",
            "datas": [
              "KR-DA-0000050758",
              "KR-DA-0000000086",
              "KR-DA-0000050756",
              "KR-DA-0000000085",
              "KR-DA-0000050755",
              "KR-DA-0000000084",
              "KR-DA-0000050759",
              "KR-DA-0000050757",
              "KR-DA-0000019549",
              "KR-DA-0000003696"
            ]
          }
        ]
      }
    ]
  },
  {
    "patterns": [
      {
        "id": "KR-PN-0000050885",
        "name": "소수와 합성수의 성질",
        "units": [
          {
            "id": "KR-UN-0000004808",
            "name": "소수와 합성수의 성질",
            "datas": [
              "KR-DA-0000019565",
              "KR-DA-0000050763",
              "KR-DA-0000003632",
              "KR-DA-0000050762",
              "KR-DA-0000050760",
              "KR-DA-0000019535",
              "KR-DA-0000050761",
              "KR-DA-0000003559",
              "KR-DA-0000011529",
              "KR-DA-0000003697",
              "KR-DA-0000050764"
            ]
          },
          {
            "id": "KR-UN-0000006907",
            "name": "소수와 합성수의 성질",
            "datas": [
              "KR-DA-0000003698",
              "KR-DA-0000011532",
              "KR-DA-0000050769",
              "KR-DA-0000003561",
              "KR-DA-0000019550",
              "KR-DA-0000050765",
              "KR-DA-0000050768",
              "KR-DA-0000003560",
              "KR-DA-0000050766",
              "KR-DA-0000050767"
            ]
          }
        ]
      }
    ]
  },
  {
    "patterns": [
      {
        "id": "KR-PN-0000050889",
        "name": "거듭제곱으로 나타내기",
        "units": [
          {
            "id": "KR-UN-0000004810",
            "name": "거듭제곱으로 나타내기",
            "datas": [
              "KR-DA-0000050777",
              "KR-DA-0000050775",
              "KR-DA-0000000092",
              "KR-DA-0000019536",
              "KR-DA-0000000091",
              "KR-DA-0000003700",
              "KR-DA-0000050778",
              "KR-DA-0000050776",
              "KR-DA-0000000090"
            ]
          },
          {
            "id": "KR-UN-0000021720",
            "name": "거듭제곱의 일의 자리의 수",
            "datas": [
              "KR-DA-0000051475",
              "KR-DA-0000051474",
              "KR-DA-0000051476",
              "KR-DA-0000051481",
              "KR-DA-0000051479",
              "KR-DA-0000051477",
              "KR-DA-0000051478",
              "KR-DA-0000051480",
              "KR-DA-0000051473"
            ]
          }
        ]
      }
    ]
  },
  {
    "patterns": [
      {
        "id": "KR-PN-0000050896",
        "name": "거듭제곱으로 나타냈을 때 밑 또는 지수 구하기",
        "units": [
          {
            "id": "KR-UN-0000004825",
            "name": "거듭제곱으로 나타냈을 때 밑 또는 지수 구하기",
            "datas": [
              "KR-DA-0000000107",
              "KR-DA-0000000108",
              "KR-DA-0000003705",
              "KR-DA-0000050836",
              "KR-DA-0000050833",
              "KR-DA-0000019553",
              "KR-DA-0000050835",
              "KR-DA-0000050837",
              "KR-DA-0000000109",
              "KR-DA-0000050834"
            ]
          },
          {
            "id": "KR-UN-0000004827",
            "name": "거듭제곱으로 나타냈을 때 밑 또는 지수 구하기",
            "datas": [
              "KR-DA-0000050838",
              "KR-DA-0000000111",
              "KR-DA-0000050842",
              "KR-DA-0000003706",
              "KR-DA-0000032586",
              "KR-DA-0000050840",
              "KR-DA-0000000110",
              "KR-DA-0000050841",
              "KR-DA-0000050839",
              "KR-DA-0000019568",
              "KR-DA-0000000112"
            ]
          },
          {
            "id": "KR-UN-0000004829",
            "name": "거듭제곱으로 나타냈을 때 밑 또는 지수 구하기",
            "datas": [
              "KR-DA-0000050851",
              "KR-DA-0000050849",
              "KR-DA-0000000119",
              "KR-DA-0000003708",
              "KR-DA-0000050850",
              "KR-DA-0000000121",
              "KR-DA-0000000120",
              "KR-DA-0000050852",
              "KR-DA-0000050848",
              "KR-DA-0000050853"
            ]
          }
        ]
      }
    ]
  }
]